py_genius/__init__.py
py_genius/py_genius.py
py_genius-0.4.0.dist-info/DESCRIPTION.rst
py_genius-0.4.0.dist-info/METADATA
py_genius-0.4.0.dist-info/RECORD
py_genius-0.4.0.dist-info/WHEEL
py_genius-0.4.0.dist-info/metadata.json
py_genius-0.4.0.dist-info/top_level.txt
