Metadata-Version: 2.0
Name: py-genius
Version: 0.4.0
Summary: A thin wrapper around the Genius API
Home-page: https://github.com/emilkloeden/py-genius
Author: Emil Kloeden
Author-email: emilkloeden@gmail.com
License: UNKNOWN
Download-URL: https://github.com/emilkloeden/py-genius/0.4.0.tar.gz
Keywords: genius
Platform: UNKNOWN
Requires-Dist: requests (>=2.13.0)
